MANIFEST.in
README.md
requirements.txt
setup.cfg
setup.py
perspective_dash_component/__init__.py
perspective_dash_component/_imports_.py
perspective_dash_component/metadata.json
perspective_dash_component/package.json
perspective_dash_component/perspective.asmjs.worker.js
perspective_dash_component/perspective.wasm.worker.js
perspective_dash_component/perspective_dash.py
perspective_dash_component/perspective_dash_component.dev.js
perspective_dash_component/perspective_dash_component.min.js
perspective_dash_component/psp.async.wasm
perspective_dash_component.egg-info/PKG-INFO
perspective_dash_component.egg-info/SOURCES.txt
perspective_dash_component.egg-info/dependency_links.txt
perspective_dash_component.egg-info/requires.txt
perspective_dash_component.egg-info/top_level.txt