Metadata-Version: 2.1
Name: perspective-dash-component
Version: 0.0.7
Summary: A dash component for perspective.
Home-page: UNKNOWN
Author: Tim Paine t.paine154@gmail.com
License: Apache-2.0
Platform: UNKNOWN
Provides-Extra: dev
